[
  {
    "name": "云游君的小站",
    "url": "https://www.yunyoujun.cn",
    "avatar": "https://www.yunyoujun.cn/images/avatar.jpg",
    "desc": "希望能成为一个有趣的人"
  },
  {
    "name": "多酱的部落格",
    "url": "https://ddindex.github.io/",
    "avatar": "https://ddindex.github.io/images/avatar.jpg",
    "desc": "双手抓楼上的大胸"
  },
  {
    "name": "神崎日照の小窝",
    "url": "https://blog.sernikki.cn/",
    "avatar": "https://blog.sernikki.cn/amiya.jpg",
    "desc": "有瑕人无玉"
  },
  {
    "name": "俺たちに翼はない",
    "url": "https://spreadwings-sky.github.io/",
    "avatar": "https://spreadwings-sky.github.io/images/avatar.png",
    "desc": "希望能成为一个有趣的人"
  },
  {
    "name": "琉的小窝",
    "url": "https://hellsakura.github.io/",
    "avatar": "https://hellsakura.github.io/images/avatar.jpg",
    "desc": "我只是一条咸鱼"
  },
  {
    "name": "nancheng58",
    "url": "https://nancheng58.github.io/",
    "avatar": "https://nancheng58.github.io/images/nancheng58.jpg",
    "desc": "我好菜啊啊啊啊啊"
  },
  {
    "name": "秩同道合的博客",
    "url": "https://alexzou14.github.io/",
    "avatar": "https://cdn.jsdelivr.net/gh/AlexZou14/CDN/img/touxiang.jpg",
    "desc": "笔记记录，自我激励"
  },
  {
    "name": "柠檬君的小站",
    "url": "http://www.romastar.cn/",
    "avatar": "https://personalblog-1301685299.cos.ap-nanjing.myqcloud.com/MyBlog-Images/Personal-Info/Avatar.jpg",
    "desc": "记录我的生活经历以及学习历程~~"
  },
  {
    "name": "山山的掉发历程",
    "url": "https://www.kumybryce.work",
    "avatar": "https://kumybryce.gitee.io/myblog/img/favicon.png",
    "desc": "努力一点，再努力一点"
  },
  {
    "name": "陌上花的小栈",
    "url": "https://hexo.cool",
    "avatar": "https://cdn.jsdelivr.net/gh/imoshanghua/file/img/avatar.jpg",
    "desc": "待我熬尽一日苦，喂你一口甜！"
  },
  {
    "name": "乐得自在的小破站",
    "url": "https://copur.xyz/",
    "avatar": "https://q1.qlogo.cn/g?b=qq&nk=1935576264&s=100",
    "desc": "乐得自在的小破站"
  },
  {
    "name": "Eden瞎写小屋",
    "url": "https://EdenJohnson2006.Github.io",
    "avatar": "https://cdn.jsdelivr.net/gh/MEMZSONBILI/PicGoBed@master/images/20200625174516.jpg",
    "desc": "希望能成为一个有趣的人"
  },
  {
    "name": "池某的小博客",
    "url": "https://chitang233.github.io/",
    "avatar": "https://s1.ax1x.com/2020/06/27/N63K8e.jpg",
    "desc": "只是一个普通的初中生罢了"
  },
  {
    "name": "偕臧",
    "url": "https://xmuli.tech",
    "avatar": "https://cdn.jsdelivr.net/gh/xmuli/xmuliPic@pic/2020/xmuli_yj_256px.png",
    "desc": "偕臧"
  },
  {
    "name": "ROGEROGER",
    "url": "https://www.rogeroger.net",
    "avatar": "https://rogeroger.oss-cn-beijing.aliyuncs.com/img/rogeryu.jpeg",
    "desc": "啊啊啊啊啊啊啊啊"
  },
  {
    "name": "LeoStudio",
    "url": "https://leostudiooo.github.io",
    "avatar": "https://avatars0.githubusercontent.com/u/35419343",
    "desc": "恰同学少年，风华正茂；书生意气，挥斥方遒。"
  },
  {
    "name": "喵二的博客",
    "url": "https://www.meow-2.com/",
    "avatar": "https://cdn.jsdelivr.net/gh/Meow-2/cdn/source/avatar.jpg",
    "desc": "你好！"
  },
  {
    "name": "SKNP的小站",
    "url": "https://sknplz.xyz/",
    "avatar": "https://cdn.jsdelivr.net/gh/Sknp1006/cdn@master/img/albums/arknights_Skadi/024.png",
    "desc": "莫道君行早，更有早行人"
  },
  {
    "name": "叶子的后花园",
    "url": "https://misaka-9936.github.io",
    "avatar": "https://misaka-9936.github.io/images/avatar/avatar.jpg",
    "desc": "后花园是自己精心培育的，大部分时候是给自己看的，不过如果有行人能够驻足欣赏，我也会很开心的！"
  },
  {
    "name": "绅士兔の小窝",
    "url": "https://gentrabbit.moe/",
    "avatar": "https://gentrabbit.moe/images/avatar.jpg",
    "desc": "To live, but not to exist."
  },
  {
    "name": "工藤旧二の博客",
    "url": "http://huang_zhao.gitee.io/task/",
    "avatar": "http://huang_zhao.gitee.io/task/Yun.png",
    "desc": "Python 是世界上最好的语言"
  },
  {
    "name": "LeiWang1999",
    "url": "https://leiblog.wang",
    "avatar": "https://leiblog.wang/images/avatar_1.jpg",
    "desc": "The warehouse of LeiWang1999"
  },
  {
    "name": "喵二の小博客",
    "url": "https://www.miaoer.xyz",
    "avatar": "https://cdn.jsdelivr.net/gh/miaoermua/miaoermua.github.io@latest/logo/weblogo.png",
    "desc": "喜欢分享一些东西 ୧(﹒ ᴗ﹒ )୨"
  },
  {
    "name": "yln's blog",
    "url": "https://www.blog.yln956.top/",
    "avatar": "https://www.blog.yln956.top/images/tou.jpg",
    "desc": "梦想是什么，梦想是现实的延续；现实是什么，现实是梦想的终结。"
  },
  {
    "name": "星云荒原",
    "url": "http://wasteland.wifikun.top",
    "avatar": "https://wifikun-1257416258.cos.ap-shanghai.myqcloud.com/NebulaStarshipServer/avatar.jpg",
    "desc": "✨Chase your passions, do what you love.✨"
  },
  {
    "name": "包子君的小站",
    "url": "https://darksheep.xyz",
    "avatar": "https://darksheep.xyz/images/avatar.jpg",
    "desc": "蹲一蹲"
  },
  {
    "name": "阿然君的小站",
    "url": "https://www.aranne.me",
    "avatar": "https://www.aranne.me/avatar.png",
    "desc": "要永远热爱生活呀"
  },
  {
    "name": "阿玮的小po站",
    "url": "https://willian588.github.io/",
    "avatar": "https://willian588.github.io/shadiao.png",
    "desc": "路漫漫其修远兮，吾将上下而求索"
  },
  {
    "name": "xczheergen",
    "url": "http://www.xczheergen.com/",
    "avatar": "https://cdn.jsdelivr.net/gh/xczheergen/CDN/images/avatar.jpg",
    "desc": "感谢云游君提供的主题哦"
  },
  {
    "name": "时前进的小站",
    "url": "https://www.eevee.fun/",
    "avatar": "https://www.eevee.fun/touxiang.PNG",
    "desc": "祝家人们天天开心，天天快乐就OK了。"
  },
  {
    "name": "林森森",
    "url": "https://assistest.github.io/",
    "avatar": "https://s.im5i.com/2021/04/03/WKnMF.jpg",
    "desc": "山有木兮木有枝,心悦君兮君不知。"
  },
  {
    "name": "熊之记事本",
    "url": "https://kuuhaku.top",
    "avatar": "https://cdn.jsdelivr.net/gh/kuuhaku-w/blogimg/intro/avatar_ai.png",
    "desc": "永远是深夜该有多好"
  },
  {
    "name": "大蛋糕的烘焙坊",
    "url": "https://bigcake.cakemc.top",
    "avatar": "https://cdn.jsdelivr.net/gh/Big-Cake-jpg/Image_For_My_Blog/tx.jpg",
    "desc": "又是搞怪的一天（"
  },
  {
    "name": "老哲的小站",
    "url": "https://masle.top",
    "avatar": "https://masle.gitee.io/maslebloglib/picture/TOUXIANG/touxiang.png",
    "desc": "在人的一生，总是为了追寻生命中的光，而走在漫长的旅途上"
  },
  {
    "name": "Adkinsm BLOG",
    "url": "https://blog.adkimsm.asia/",
    "avatar": "https://blog.adkimsm.asia/logo.svg",
    "desc": "Adkinsm 的小站"
  },
  {
    "name": "MleMoe",
    "url": "https://blog.mle.moe/",
    "avatar": "https://blog.mle.moe/images/girl.jpeg",
    "desc": "鸽子的一百种做法"
  },
  {
    "name": "七月流火",
    "url": "https://qylh.xyz/",
    "avatar": "https://qylh.xyz/avatar.jpg",
    "desc": "记录一些学习过程，主要是软硬件开发"
  },
  {
    "name": "泠风寒声的小窝",
    "url": "https://lfhsheng.github.io/",
    "avatar": "https://lfhsheng.github.io/images/lfhsheng.jpg",
    "desc": "沉浸在Touch Fish的海洋中无法自拔"
  },
  {
    "name": "Yuumi的烟波之路",
    "url": "https://yuumi0221.github.io/",
    "avatar": "https://cdn.jsdelivr.net/gh/Yuumi0221/Yuumi0221.github.io/images/settings/favicon.png",
    "desc": "いつか伝えに行くよ"
  },
  {
    "name": "你看起来很好吃",
    "url": "https://Melanie618.github.io/",
    "avatar": "https://melanie618.github.io/images/avatar.jpg",
    "desc": "可可爱爱，没有脑袋"
  },
  {
    "name": "落梅听风雪",
    "url": "https://yuexiaoya.cn/",
    "avatar": "https://www.yuexiaoya.cn/images/photo.jpg",
    "desc": "这次一定不会让它停服了,来自头号玩家的碎碎念^_^"
  },
  {
    "name": "小文的博客",
    "url": "https://siquan-wen.github.io/",
    "avatar": "https://github.com/SiQuan-Wen/SiQuan-Wen.github.io/blob/hexo/source/images/avatar.jpg",
    "desc": "救赎之道，就在其中"
  }
]
